fastrepl/__init__.py
fastrepl/analyze.py
fastrepl/dataset.py
fastrepl/errors.py
fastrepl/eval/__init__.py
fastrepl/eval/base.py
fastrepl/eval/evaluator.py
fastrepl/eval/human/__init__.py
fastrepl/eval/human/classify.py
fastrepl/eval/metric/__init__.py
fastrepl/eval/metric/huggingface.py
fastrepl/eval/metric/load.py
fastrepl/eval/metric/sas.py
fastrepl/eval/model/__init__.py
fastrepl/eval/model/llm_head.py
fastrepl/eval/model/llm_head_cot.py
fastrepl/eval/model/ragas.py
fastrepl/eval/model/utils.py
fastrepl/gen/__init__.py
fastrepl/gen/base.py
fastrepl/gen/question.py
fastrepl/llama_index.py
fastrepl/llm.py
fastrepl/runner/__init__.py
fastrepl/runner/base.py
fastrepl/runner/custom.py
fastrepl/runner/evaluator.py
fastrepl/runner/generator.py
fastrepl/runner/promptlayer.py
fastrepl/telemetry.py
fastrepl/test_utils.py
fastrepl/unittests_class.py
fastrepl/utils/__init__.py
fastrepl/utils/context.py
fastrepl/utils/data_structure.py
fastrepl/utils/debug.py
fastrepl/utils/ensure.py
fastrepl/utils/env.py
fastrepl/utils/id.py
fastrepl/utils/iterator.py
fastrepl/utils/kappa.py
fastrepl/utils/llm.py
fastrepl/utils/number.py
fastrepl/utils/print.py
fastrepl/utils/prompt.py
fastrepl/utils/string.py
fastrepl/version.py
fastrepl/warnings.py
fastrepl-0.0.25.dist-info/LICENSE
fastrepl-0.0.25.dist-info/METADATA
fastrepl-0.0.25.dist-info/WHEEL
fastrepl-0.0.25.dist-info/RECORD
