Metadata-Version: 2.1
Name: fastrepl
Version: 0.0.25
Summary: Fast Run-Eval-Polish Loop for LLM App
License: MIT
Author: yujonglee
Author-email: yujonglee@repllabs.ai
Requires-Python: >=3.9,<3.12
Classifier: License :: OSI Approved :: MIT License
Classifier: Programming Language :: Python :: 3
Classifier: Programming Language :: Python :: 3.9
Classifier: Programming Language :: Python :: 3.10
Classifier: Programming Language :: Python :: 3.11
Provides-Extra: langfuse
Provides-Extra: ragas
Provides-Extra: sas
Requires-Dist: backoff (>=2.2.1,<3.0.0)
Requires-Dist: cohere (>=4.20.2,<5.0.0)
Requires-Dist: cuid2 (>=2.0.0,<3.0.0)
Requires-Dist: datasets (>=2.14.4,<3.0.0) ; extra == "ragas"
Requires-Dist: evaluate (>=0.4.0,<0.5.0)
Requires-Dist: httpx (>=0.24.0)
Requires-Dist: iprogress (>=0.4,<0.5)
Requires-Dist: langfuse (>=1.0.35) ; extra == "langfuse"
Requires-Dist: litellm (>=0.8.4,<0.9.0)
Requires-Dist: openai (>=0.27.8,<0.28.0)
Requires-Dist: ragas (>=0.0.16) ; extra == "ragas"
Requires-Dist: rich[jupyter] (>=13.5.2,<14.0.0)
Requires-Dist: scikit-learn (>=1.3.0,<2.0.0)
Requires-Dist: sentence-transformers (>=2.2.2,<3.0.0) ; extra == "sas"
Requires-Dist: statsmodels (>=0.14.0,<0.15.0)
Requires-Dist: tiktoken (>=0.4.0,<0.5.0)
Requires-Dist: torch (>=2.0.0,!=2.0.1) ; extra == "sas"
Requires-Dist: transformers (>=4.31.0,<5.0.0) ; extra == "sas"
Requires-Dist: wrapt-timeout-decorator (>=1.4.0,<2.0.0)
